balderhub/guicontrol/__init__.py
balderhub/guicontrol/_version.py
balderhub/guicontrol/lib/__init__.py
balderhub/guicontrol/lib/scenario_features/__init__.py
balderhub/guicontrol/lib/scenario_features/gui_control_feature.py
balderhub/guicontrol/lib/utils/__init__.py
balderhub/guicontrol/lib/utils/driver/__init__.py
balderhub/guicontrol/lib/utils/driver/base_driver_class.py
balderhub/guicontrol/lib/utils/element_bridges/__init__.py
balderhub/guicontrol/lib/utils/element_bridges/base_element_bridge.py
balderhub_guicontrol-0.0.1b0.dist-info/licenses/LICENSE
balderhub_guicontrol-0.0.1b0.dist-info/METADATA
balderhub_guicontrol-0.0.1b0.dist-info/WHEEL
balderhub_guicontrol-0.0.1b0.dist-info/top_level.txt
balderhub_guicontrol-0.0.1b0.dist-info/RECORD
